{"school_name": "lafayette college", "school_forbes_uri": "lafayette-college", "school_forbes_abs_uri": "https://www.forbes.com/colleges/lafayette-college", "rankings": [{"category_name": "Top Colleges 2019", "category_ranking": "57"}, {"category_name": "In Private Colleges", "category_ranking": "47"}, {"category_name": "In Liberal Arts Universities", "category_ranking": "23"}, {"category_name": "In The Northeast", "category_ranking": "30"}, {"category_name": "America's Best Value Colleges 2019", "category_ranking": "199"}]}