[{"name": "Stanford University", "country": "United States", "ranking_categories": [{"category_name": "overall", "category_score": "88.6", "category_rank": "1"}, {"category_name": "teaching", "category_score": "92.2", "category_rank": "2"}, {"category_name": "international_outlook", "category_score": "70.0", "category_rank": "23"}, {"category_name": "industry_income", "category_score": "-", "category_rank": "88"}, {"category_name": "research", "category_score": "92.9", "category_rank": "5"}, {"category_name": "citations", "category_score": "81.6", "category_rank": "2"}]}, {"name": "Harvard University", "country": "United States", "ranking_categories": [{"category_name": "overall", "category_score": "86.6", "category_rank": "2"}, {"category_name": "teaching", "category_score": "92.5", "category_rank": "1"}, {"category_name": "international_outlook", "category_score": "66.1", "category_rank": "31"}, {"category_name": "industry_income", "category_score": "36.9", "category_rank": "64"}, {"category_name": "research", "category_score": "93.4", "category_rank": "4"}, {"category_name": "citations", "category_score": "73.3", "category_rank": "8"}]}, {"name": "The University of Chicago", "country": "United States", "ranking_categories": [{"category_name": "overall", "category_score": "85.9", "category_rank": "3"}, {"category_name": "teaching", "category_score": "88.8", "category_rank": "7"}, {"category_name": "international_outlook", "category_score": "64.0", "category_rank": "35"}, {"category_name": "industry_income", "category_score": "-", "category_rank": "92"}, {"category_name": "research", "category_score": "95.5", "category_rank": "2"}, {"category_name": "citations", "category_score": "67.6", "category_rank": "25"}]}, {"name": "University of Cambridge", "country": "United Kingdom", "ranking_categories": [{"category_name": "overall", "category_score": "84.7", "category_rank": "4"}, {"category_name": "teaching", "category_score": "90.9", "category_rank": "3"}, {"category_name": "international_outlook", "category_score": "72.1", "category_rank": "17"}, {"category_name": "industry_income", "category_score": "53.3", "category_rank": "15"}, {"category_name": "research", "category_score": "95.8", "category_rank": "1"}, {"category_name": "citations", "category_score": "52.5", "category_rank": "68"}]}, {"name": "University of Oxford", "country": "United Kingdom", "ranking_categories": [{"category_name": "overall", "category_score": "84.2", "category_rank": "5"}, {"category_name": "teaching", "category_score": "89.1", "category_rank": "6"}, {"category_name": "international_outlook", "category_score": "72.4", "category_rank": "16"}, {"category_name": "industry_income", "category_score": "37.6", "category_rank": "54"}, {"category_name": "research", "category_score": "95.1", "category_rank": "3"}, {"category_name": "citations", "category_score": "57.9", "category_rank": "51"}]}, {"name": "Princeton University", "country": "United States", "ranking_categories": [{"category_name": "overall", "category_score": "82.9", "category_rank": "6"}, {"category_name": "teaching", "category_score": "90.2", "category_rank": "4"}, {"category_name": "international_outlook", "category_score": "50.5", "category_rank": "64"}, {"category_name": "industry_income", "category_score": "53.0", "category_rank": "17"}, {"category_name": "research", "category_score": "91.9", "category_rank": "7"}, {"category_name": "citations", "category_score": "63.4", "category_rank": "37"}]}, {"name": "Yale University", "country": "United States", "ranking_categories": [{"category_name": "overall", "category_score": "82.1", "category_rank": "7"}, {"category_name": "teaching", "category_score": "89.7", "category_rank": "5"}, {"category_name": "international_outlook", "category_score": "61.2", "category_rank": "46"}, {"category_name": "industry_income", "category_score": "41.1", "category_rank": "30"}, {"category_name": "research", "category_score": "92.6", "category_rank": "6"}, {"category_name": "citations", "category_score": "54.3", "category_rank": "63"}]}, {"name": "UCL", "country": "United Kingdom", "ranking_categories": [{"category_name": "overall", "category_score": "80.8", "category_rank": "8"}, {"category_name": "teaching", "category_score": "83.2", "category_rank": "11"}, {"category_name": "international_outlook", "category_score": "84.8", "category_rank": "3"}, {"category_name": "industry_income", "category_score": "42.2", "category_rank": "27"}, {"category_name": "research", "category_score": "88.4", "category_rank": "10"}, {"category_name": "citations", "category_score": "59.8", "category_rank": "49"}]}, {"name": "University of California, Berkeley", "country": "United States", "ranking_categories": [{"category_name": "overall", "category_score": "80.6", "category_rank": "9"}, {"category_name": "teaching", "category_score": "87.5", "category_rank": "8"}, {"category_name": "international_outlook", "category_score": "56.8", "category_rank": "54"}, {"category_name": "industry_income", "category_score": "-", "category_rank": "89"}, {"category_name": "research", "category_score": "86.1", "category_rank": "12"}, {"category_name": "citations", "category_score": "64.6", "category_rank": "33"}]}, {"name": "University of California, Los Angeles", "country": "United States", "ranking_categories": [{"category_name": "overall", "category_score": "79.8", "category_rank": "10"}, {"category_name": "teaching", "category_score": "84.6", "category_rank": "10"}, {"category_name": "international_outlook", "category_score": "41.4", "category_rank": "80"}, {"category_name": "industry_income", "category_score": "-", "category_rank": "90"}, {"category_name": "research", "category_score": "89.8", "category_rank": "8"}, {"category_name": "citations", "category_score": "68.0", "category_rank": "23"}]}, {"name": "Columbia University", "country": "United States", "ranking_categories": [{"category_name": "overall", "category_score": "79.4", "category_rank": "11"}, {"category_name": "teaching", "category_score": "85.3", "category_rank": "9"}, {"category_name": "international_outlook", "category_score": "54.7", "category_rank": "57"}, {"category_name": "industry_income", "category_score": "-", "category_rank": "77"}, {"category_name": "research", "category_score": "84.1", "category_rank": "14"}, {"category_name": "citations", "category_score": "68.3", "category_rank": "21"}]}, {"name": "University of Edinburgh", "country": "United Kingdom", "ranking_categories": [{"category_name": "overall", "category_score": "77.9", "category_rank": "12"}, {"category_name": "teaching", "category_score": "79.4", "category_rank": "14"}, {"category_name": "international_outlook", "category_score": "76.1", "category_rank": "11"}, {"category_name": "industry_income", "category_score": "40.9", "category_rank": "31"}, {"category_name": "research", "category_score": "86.0", "category_rank": "13"}, {"category_name": "citations", "category_score": "60.6", "category_rank": "45"}]}, {"name": "University of Pennsylvania", "country": "United States", "ranking_categories": [{"category_name": "overall", "category_score": "76.4", "category_rank": "13"}, {"category_name": "teaching", "category_score": "82.5", "category_rank": "12"}, {"category_name": "international_outlook", "category_score": "59.7", "category_rank": "49"}, {"category_name": "industry_income", "category_score": "-", "category_rank": "96"}, {"category_name": "research", "category_score": "75.1", "category_rank": "22"}, {"category_name": "citations", "category_score": "73.6", "category_rank": "7"}]}, {"name": "New York University", "country": "United States", "ranking_categories": [{"category_name": "overall", "category_score": "76.2", "category_rank": "14"}, {"category_name": "teaching", "category_score": "80.6", "category_rank": "13"}, {"category_name": "international_outlook", "category_score": "50.0", "category_rank": "66"}, {"category_name": "industry_income", "category_score": "-", "category_rank": "86"}, {"category_name": "research", "category_score": "82.8", "category_rank": "16"}, {"category_name": "citations", "category_score": "65.7", "category_rank": "29"}]}, {"name": "University of Toronto", "country": "Canada", "ranking_categories": [{"category_name": "overall", "category_score": "75.6", "category_rank": "15"}, {"category_name": "teaching", "category_score": "77.1", "category_rank": "15"}, {"category_name": "international_outlook", "category_score": "44.4", "category_rank": "74"}, {"category_name": "industry_income", "category_score": "36.8", "category_rank": "73"}, {"category_name": "research", "category_score": "87.3", "category_rank": "11"}, {"category_name": "citations", "category_score": "64.6", "category_rank": "34"}]}, {"name": "Australian National University", "country": "Australia", "ranking_categories": [{"category_name": "overall", "category_score": "75.2", "category_rank": "16"}, {"category_name": "teaching", "category_score": "64.6", "category_rank": "30"}, {"category_name": "international_outlook", "category_score": "75.5", "category_rank": "14"}, {"category_name": "industry_income", "category_score": "41.5", "category_rank": "28"}, {"category_name": "research", "category_score": "88.9", "category_rank": "9"}, {"category_name": "citations", "category_score": "72.7", "category_rank": "10"}]}, {"name": "University of Michigan-Ann Arbor", "country": "United States", "ranking_categories": [{"category_name": "overall", "category_score": "74.4", "category_rank": "17"}, {"category_name": "teaching", "category_score": "76.3", "category_rank": "17"}, {"category_name": "international_outlook", "category_score": "39.4", "category_rank": "82"}, {"category_name": "industry_income", "category_score": "38.9", "category_rank": "41"}, {"category_name": "research", "category_score": "83.5", "category_rank": "15"}, {"category_name": "citations", "category_score": "70.5", "category_rank": "15"}]}, {"name": "University of Sydney", "country": "Australia", "ranking_categories": [{"category_name": "overall", "category_score": "72.1", "category_rank": "18"}, {"category_name": "teaching", "category_score": "73.2", "category_rank": "20"}, {"category_name": "international_outlook", "category_score": "76.1", "category_rank": "12"}, {"category_name": "industry_income", "category_score": "45.0", "category_rank": "24"}, {"category_name": "research", "category_score": "75.2", "category_rank": "20"}, {"category_name": "citations", "category_score": "64.4", "category_rank": "35"}]}, {"name": "University of Melbourne", "country": "Australia", "ranking_categories": [{"category_name": "overall", "category_score": "71.9", "category_rank": "19"}, {"category_name": "teaching", "category_score": "76.9", "category_rank": "16"}, {"category_name": "international_outlook", "category_score": "78.5", "category_rank": "8"}, {"category_name": "industry_income", "category_score": "54.1", "category_rank": "13"}, {"category_name": "research", "category_score": "76.5", "category_rank": "19"}, {"category_name": "citations", "category_score": "47.6", "category_rank": "79"}]}, {"name": "Duke University", "country": "United States", "ranking_categories": [{"category_name": "overall", "category_score": "71.1", "category_rank": "20"}, {"category_name": "teaching", "category_score": "71.4", "category_rank": "21"}, {"category_name": "international_outlook", "category_score": "62.3", "category_rank": "39"}, {"category_name": "industry_income", "category_score": "-", "category_rank": "79"}, {"category_name": "research", "category_score": "70.6", "category_rank": "26"}, {"category_name": "citations", "category_score": "76.5", "category_rank": "5"}]}, {"name": "Cornell University", "country": "United States", "ranking_categories": [{"category_name": "overall", "category_score": "70.7", "category_rank": "21"}, {"category_name": "teaching", "category_score": "76.0", "category_rank": "18"}, {"category_name": "international_outlook", "category_score": "37.6", "category_rank": "86"}, {"category_name": "industry_income", "category_score": "36.8", "category_rank": "68"}, {"category_name": "research", "category_score": "75.1", "category_rank": "21"}, {"category_name": "citations", "category_score": "68.7", "category_rank": "20"}]}, {"name": "LMU Munich", "country": "Germany", "ranking_categories": [{"category_name": "overall", "category_score": "70.4", "category_rank": "22"}, {"category_name": "teaching", "category_score": "73.6", "category_rank": "19"}, {"category_name": "international_outlook", "category_score": "63.9", "category_rank": "36"}, {"category_name": "industry_income", "category_score": "73.5", "category_rank": "6"}, {"category_name": "research", "category_score": "78.4", "category_rank": "17"}, {"category_name": "citations", "category_score": "45.4", "category_rank": "85"}]}, {"name": "King\u2019s College London", "country": "United Kingdom", "ranking_categories": [{"category_name": "overall", "category_score": "69.7", "category_rank": "23"}, {"category_name": "teaching", "category_score": "70.0", "category_rank": "23"}, {"category_name": "international_outlook", "category_score": "78.6", "category_rank": "7"}, {"category_name": "industry_income", "category_score": "36.8", "category_rank": "70"}, {"category_name": "research", "category_score": "75.0", "category_rank": "23"}, {"category_name": "citations", "category_score": "56.4", "category_rank": "57"}]}, {"name": "Free University of Berlin", "country": "Germany", "ranking_categories": [{"category_name": "overall", "category_score": "67.4", "category_rank": "24"}, {"category_name": "teaching", "category_score": "71.2", "category_rank": "22"}, {"category_name": "international_outlook", "category_score": "56.0", "category_rank": "55"}, {"category_name": "industry_income", "category_score": "38.4", "category_rank": "44"}, {"category_name": "research", "category_score": "77.8", "category_rank": "18"}, {"category_name": "citations", "category_score": "42.7", "category_rank": "94"}]}, {"name": "Leiden University", "country": "Netherlands", "ranking_categories": [{"category_name": "overall", "category_score": "65.9", "category_rank": "25"}, {"category_name": "teaching", "category_score": "68.8", "category_rank": "25"}, {"category_name": "international_outlook", "category_score": "67.3", "category_rank": "26"}, {"category_name": "industry_income", "category_score": "38.2", "category_rank": "45"}, {"category_name": "research", "category_score": "73.4", "category_rank": "24"}, {"category_name": "citations", "category_score": "43.7", "category_rank": "89"}]}, {"name": "McGill University", "country": "Canada", "ranking_categories": [{"category_name": "overall", "category_score": "65.2", "category_rank": "26"}, {"category_name": "teaching", "category_score": "65.0", "category_rank": "28"}, {"category_name": "international_outlook", "category_score": "84.7", "category_rank": "4"}, {"category_name": "industry_income", "category_score": "-", "category_rank": "85"}, {"category_name": "research", "category_score": "63.9", "category_rank": "34"}, {"category_name": "citations", "category_score": "62.2", "category_rank": "41"}]}, {"name": "Humboldt University of Berlin", "country": "Germany", "ranking_categories": [{"category_name": "overall", "category_score": "65.1", "category_rank": "27"}, {"category_name": "teaching", "category_score": "69.4", "category_rank": "24"}, {"category_name": "international_outlook", "category_score": "59.1", "category_rank": "52"}, {"category_name": "industry_income", "category_score": "-", "category_rank": "83"}, {"category_name": "research", "category_score": "71.2", "category_rank": "25"}, {"category_name": "citations", "category_score": "43.2", "category_rank": "93"}]}, {"name": "University of Manchester", "country": "United Kingdom", "ranking_categories": [{"category_name": "overall", "category_score": "64.6", "category_rank": "28"}, {"category_name": "teaching", "category_score": "62.6", "category_rank": "32"}, {"category_name": "international_outlook", "category_score": "67.1", "category_rank": "27"}, {"category_name": "industry_income", "category_score": "37.0", "category_rank": "62"}, {"category_name": "research", "category_score": "64.2", "category_rank": "32"}, {"category_name": "citations", "category_score": "74.2", "category_rank": "6"}]}, {"name": "University of Texas at Austin", "country": "United States", "ranking_categories": [{"category_name": "overall", "category_score": "63.7", "category_rank": "29"}, {"category_name": "teaching", "category_score": "65.5", "category_rank": "26"}, {"category_name": "international_outlook", "category_score": "32.0", "category_rank": "97"}, {"category_name": "industry_income", "category_score": "39.2", "category_rank": "39"}, {"category_name": "research", "category_score": "66.5", "category_rank": "29"}, {"category_name": "citations", "category_score": "72.2", "category_rank": "12"}]}, {"name": "University of Wisconsin-Madison", "country": "United States", "ranking_categories": [{"category_name": "overall", "category_score": "63.4", "category_rank": "30"}, {"category_name": "teaching", "category_score": "59.1", "category_rank": "36"}, {"category_name": "international_outlook", "category_score": "41.8", "category_rank": "79"}, {"category_name": "industry_income", "category_score": "42.7", "category_rank": "25"}, {"category_name": "research", "category_score": "67.4", "category_rank": "28"}, {"category_name": "citations", "category_score": "78.1", "category_rank": "4"}]}, {"name": "Heidelberg University", "country": "Germany", "ranking_categories": [{"category_name": "overall", "category_score": "61.8", "category_rank": "31"}, {"category_name": "teaching", "category_score": "64.9", "category_rank": "29"}, {"category_name": "international_outlook", "category_score": "67.9", "category_rank": "25"}, {"category_name": "industry_income", "category_score": "37.4", "category_rank": "57"}, {"category_name": "research", "category_score": "66.4", "category_rank": "30"}, {"category_name": "citations", "category_score": "43.6", "category_rank": "90"}]}, {"name": "Rutgers, the State University of New Jersey", "country": "United States", "ranking_categories": [{"category_name": "overall", "category_score": "60.6", "category_rank": "32"}, {"category_name": "teaching", "category_score": "55.6", "category_rank": "41"}, {"category_name": "international_outlook", "category_score": "33.3", "category_rank": "94"}, {"category_name": "industry_income", "category_score": "-", "category_rank": "87"}, {"category_name": "research", "category_score": "68.2", "category_rank": "27"}, {"category_name": "citations", "category_score": "70.5", "category_rank": "14"}]}, {"name": "University of St Andrews", "country": "United Kingdom", "ranking_categories": [{"category_name": "overall", "category_score": "60.4", "category_rank": "33"}, {"category_name": "teaching", "category_score": "61.3", "category_rank": "33"}, {"category_name": "international_outlook", "category_score": "78.1", "category_rank": "9"}, {"category_name": "industry_income", "category_score": "37.5", "category_rank": "56"}, {"category_name": "research", "category_score": "64.0", "category_rank": "33"}, {"category_name": "citations", "category_score": "43.9", "category_rank": "87"}]}, {"name": "Durham University", "country": "United Kingdom", "ranking_categories": [{"category_name": "overall", "category_score": "60.0", "category_rank": "34"}, {"category_name": "teaching", "category_score": "63.0", "category_rank": "31"}, {"category_name": "international_outlook", "category_score": "62.3", "category_rank": "40"}, {"category_name": "industry_income", "category_score": "46.5", "category_rank": "21"}, {"category_name": "research", "category_score": "59.4", "category_rank": "40"}, {"category_name": "citations", "category_score": "55.2", "category_rank": "60"}]}, {"name": "University of North Carolina at Chapel Hill", "country": "United States", "ranking_categories": [{"category_name": "overall", "category_score": "59.3", "category_rank": "35"}, {"category_name": "teaching", "category_score": "60.3", "category_rank": "35"}, {"category_name": "international_outlook", "category_score": "35.1", "category_rank": "91"}, {"category_name": "industry_income", "category_score": "39.3", "category_rank": "37"}, {"category_name": "research", "category_score": "64.3", "category_rank": "31"}, {"category_name": "citations", "category_score": "59.9", "category_rank": "48"}]}, {"name": "Lancaster University", "country": "United Kingdom", "ranking_categories": [{"category_name": "overall", "category_score": "59.0", "category_rank": "36"}, {"category_name": "teaching", "category_score": "58.0", "category_rank": "37"}, {"category_name": "international_outlook", "category_score": "66.6", "category_rank": "29"}, {"category_name": "industry_income", "category_score": "36.9", "category_rank": "65"}, {"category_name": "research", "category_score": "54.3", "category_rank": "47"}, {"category_name": "citations", "category_score": "73.3", "category_rank": "9"}]}, {"name": "Brown University", "country": "United States", "ranking_categories": [{"category_name": "overall", "category_score": "58.3", "category_rank": "37"}, {"category_name": "teaching", "category_score": "65.1", "category_rank": "27"}, {"category_name": "international_outlook", "category_score": "50.0", "category_rank": "65"}, {"category_name": "industry_income", "category_score": "-", "category_rank": "76"}, {"category_name": "research", "category_score": "56.8", "category_rank": "42"}, {"category_name": "citations", "category_score": "50.2", "category_rank": "74"}]}, {"name": "University of Vienna", "country": "Austria", "ranking_categories": [{"category_name": "overall", "category_score": "57.9", "category_rank": "38"}, {"category_name": "teaching", "category_score": "57.6", "category_rank": "39"}, {"category_name": "international_outlook", "category_score": "65.6", "category_rank": "33"}, {"category_name": "industry_income", "category_score": "-", "category_rank": "98"}, {"category_name": "research", "category_score": "61.2", "category_rank": "36"}, {"category_name": "citations", "category_score": "48.0", "category_rank": "78"}]}, {"name": "University of Notre Dame", "country": "United States", "ranking_categories": [{"category_name": "overall", "category_score": "57.7", "category_rank": "39"}, {"category_name": "teaching", "category_score": "60.9", "category_rank": "34"}, {"category_name": "international_outlook", "category_score": "39.0", "category_rank": "83"}, {"category_name": "industry_income", "category_score": "-", "category_rank": "95"}, {"category_name": "research", "category_score": "60.8", "category_rank": "38"}, {"category_name": "citations", "category_score": "51.8", "category_rank": "70"}]}, {"name": "University of British Columbia", "country": "Canada", "ranking_categories": [{"category_name": "overall", "category_score": "57.3", "category_rank": "40"}, {"category_name": "teaching", "category_score": "52.7", "category_rank": "45"}, {"category_name": "international_outlook", "category_score": "65.8", "category_rank": "32"}, {"category_name": "industry_income", "category_score": "37.0", "category_rank": "61"}, {"category_name": "research", "category_score": "55.7", "category_rank": "45"}, {"category_name": "citations", "category_score": "71.9", "category_rank": "13"}]}, {"name": "KU Leuven", "country": "Belgium", "ranking_categories": [{"category_name": "overall", "category_score": "56.8", "category_rank": "41"}, {"category_name": "teaching", "category_score": "53.1", "category_rank": "44"}, {"category_name": "international_outlook", "category_score": "62.1", "category_rank": "41"}, {"category_name": "industry_income", "category_score": "98.8", "category_rank": "1"}, {"category_name": "research", "category_score": "60.8", "category_rank": "37"}, {"category_name": "citations", "category_score": "46.7", "category_rank": "82"}]}, {"name": "National University of Singapore", "country": "Singapore", "ranking_categories": [{"category_name": "overall", "category_score": "56.7", "category_rank": "42"}, {"category_name": "teaching", "category_score": "57.6", "category_rank": "38"}, {"category_name": "international_outlook", "category_score": "89.3", "category_rank": "1"}, {"category_name": "industry_income", "category_score": "38.6", "category_rank": "43"}, {"category_name": "research", "category_score": "53.8", "category_rank": "48"}, {"category_name": "citations", "category_score": "48.6", "category_rank": "77"}]}, {"name": "University of Hong Kong", "country": "Hong Kong", "ranking_categories": [{"category_name": "overall", "category_score": "56.0", "category_rank": "43"}, {"category_name": "teaching", "category_score": "50.6", "category_rank": "48"}, {"category_name": "international_outlook", "category_score": "86.9", "category_rank": "2"}, {"category_name": "industry_income", "category_score": "53.9", "category_rank": "14"}, {"category_name": "research", "category_score": "59.5", "category_rank": "39"}, {"category_name": "citations", "category_score": "45.4", "category_rank": "86"}]}, {"name": "Monash University", "country": "Australia", "ranking_categories": [{"category_name": "overall", "category_score": "55.6", "category_rank": "44"}, {"category_name": "teaching", "category_score": "56.7", "category_rank": "40"}, {"category_name": "international_outlook", "category_score": "76.4", "category_rank": "10"}, {"category_name": "industry_income", "category_score": "64.4", "category_rank": "10"}, {"category_name": "research", "category_score": "54.6", "category_rank": "46"}, {"category_name": "citations", "category_score": "43.4", "category_rank": "92"}]}, {"name": "University of Amsterdam", "country": "Netherlands", "ranking_categories": [{"category_name": "overall", "category_score": "55.1", "category_rank": "45"}, {"category_name": "teaching", "category_score": "48.3", "category_rank": "52"}, {"category_name": "international_outlook", "category_score": "59.3", "category_rank": "51"}, {"category_name": "industry_income", "category_score": "41.2", "category_rank": "29"}, {"category_name": "research", "category_score": "62.7", "category_rank": "35"}, {"category_name": "citations", "category_score": "53.4", "category_rank": "65"}]}, {"name": "University of Warwick", "country": "United Kingdom", "ranking_categories": [{"category_name": "overall", "category_score": "53.7", "category_rank": "46"}, {"category_name": "teaching", "category_score": "48.6", "category_rank": "51"}, {"category_name": "international_outlook", "category_score": "60.3", "category_rank": "48"}, {"category_name": "industry_income", "category_score": "36.8", "category_rank": "74"}, {"category_name": "research", "category_score": "55.9", "category_rank": "44"}, {"category_name": "citations", "category_score": "60.2", "category_rank": "47"}]}, {"name": "University of T\u00fcbingen", "country": "Germany", "ranking_categories": [{"category_name": "overall", "category_score": "53.6", "category_rank": "47"}, {"category_name": "teaching", "category_score": "54.2", "category_rank": "43"}, {"category_name": "international_outlook", "category_score": "42.7", "category_rank": "76"}, {"category_name": "industry_income", "category_score": "57.9", "category_rank": "11"}, {"category_name": "research", "category_score": "51.0", "category_rank": "50"}, {"category_name": "citations", "category_score": "63.1", "category_rank": "39"}]}, {"name": "University of Massachusetts", "country": "United States", "ranking_categories": [{"category_name": "overall", "category_score": "53.3", "category_rank": "48"}, {"category_name": "teaching", "category_score": "50.9", "category_rank": "47"}, {"category_name": "international_outlook", "category_score": "34.4", "category_rank": "93"}, {"category_name": "industry_income", "category_score": "39.2", "category_rank": "38"}, {"category_name": "research", "category_score": "56.6", "category_rank": "43"}, {"category_name": "citations", "category_score": "63.1", "category_rank": "38"}]}, {"name": "Birkbeck, University of London", "country": "United Kingdom", "ranking_categories": [{"category_name": "overall", "category_score": "51.9", "category_rank": "49"}, {"category_name": "teaching", "category_score": "48.0", "category_rank": "54"}, {"category_name": "international_outlook", "category_score": "70.5", "category_rank": "22"}, {"category_name": "industry_income", "category_score": "36.9", "category_rank": "63"}, {"category_name": "research", "category_score": "46.2", "category_rank": "57"}, {"category_name": "citations", "category_score": "68.9", "category_rank": "19"}]}, {"name": "\u00c9cole Normale Sup\u00e9rieure", "country": "France", "ranking_categories": [{"category_name": "overall", "category_score": "51.8", "category_rank": "50"}, {"category_name": "teaching", "category_score": "47.6", "category_rank": "56"}, {"category_name": "international_outlook", "category_score": "66.2", "category_rank": "30"}, {"category_name": "industry_income", "category_score": "-", "category_rank": "80"}, {"category_name": "research", "category_score": "42.8", "category_rank": "67"}, {"category_name": "citations", "category_score": "78.9", "category_rank": "3"}]}, {"name": "University of Birmingham", "country": "United Kingdom", "ranking_categories": [{"category_name": "overall", "category_score": "50.8", "category_rank": "51"}, {"category_name": "teaching", "category_score": "50.5", "category_rank": "49"}, {"category_name": "international_outlook", "category_score": "57.7", "category_rank": "53"}, {"category_name": "industry_income", "category_score": "45.7", "category_rank": "23"}, {"category_name": "research", "category_score": "47.2", "category_rank": "54"}, {"category_name": "citations", "category_score": "57.9", "category_rank": "50"}]}, {"name": "University of Southern California", "country": "United States", "ranking_categories": [{"category_name": "overall", "category_score": "50.3", "category_rank": "52"}, {"category_name": "teaching", "category_score": "52.2", "category_rank": "46"}, {"category_name": "international_outlook", "category_score": "37.0", "category_rank": "87"}, {"category_name": "industry_income", "category_score": "-", "category_rank": "97"}, {"category_name": "research", "category_score": "48.9", "category_rank": "51"}, {"category_name": "citations", "category_score": "56.7", "category_rank": "56"}]}, {"name": "University of Pittsburgh-Pittsburgh campus", "country": "United States", "ranking_categories": [{"category_name": "overall", "category_score": "50.1", "category_rank": "53"}, {"category_name": "teaching", "category_score": "41.2", "category_rank": "72"}, {"category_name": "international_outlook", "category_score": "36.8", "category_rank": "89"}, {"category_name": "industry_income", "category_score": "38.2", "category_rank": "46"}, {"category_name": "research", "category_score": "57.6", "category_rank": "41"}, {"category_name": "citations", "category_score": "62.7", "category_rank": "40"}]}, {"name": "University of Auckland", "country": "New Zealand", "ranking_categories": [{"category_name": "overall", "category_score": "49.8", "category_rank": "54"}, {"category_name": "teaching", "category_score": "49.6", "category_rank": "50"}, {"category_name": "international_outlook", "category_score": "72.4", "category_rank": "15"}, {"category_name": "industry_income", "category_score": "76.2", "category_rank": "4"}, {"category_name": "research", "category_score": "42.5", "category_rank": "68"}, {"category_name": "citations", "category_score": "52.9", "category_rank": "66"}]}, {"name": "University of California, Santa Barbara", "country": "United States", "ranking_categories": [{"category_name": "overall", "category_score": "49.5", "category_rank": "55"}, {"category_name": "teaching", "category_score": "47.0", "category_rank": "58"}, {"category_name": "international_outlook", "category_score": "49.7", "category_rank": "67"}, {"category_name": "industry_income", "category_score": "55.6", "category_rank": "12"}, {"category_name": "research", "category_score": "48.4", "category_rank": "52"}, {"category_name": "citations", "category_score": "57.1", "category_rank": "55"}]}, {"name": "London School of Economics and Political Science", "country": "United Kingdom", "ranking_categories": [{"category_name": "overall", "category_score": "48.6", "category_rank": "56"}, {"category_name": "teaching", "category_score": "36.6", "category_rank": "80"}, {"category_name": "international_outlook", "category_score": "20.2", "category_rank": "101"}, {"category_name": "industry_income", "category_score": "-", "category_rank": "84"}, {"category_name": "research", "category_score": "52.6", "category_rank": "49"}, {"category_name": "citations", "category_score": "90.9", "category_rank": "1"}]}, {"name": "Georgetown University", "country": "United States", "ranking_categories": [{"category_name": "overall", "category_score": "48.5", "category_rank": "57"}, {"category_name": "teaching", "category_score": "55.5", "category_rank": "42"}, {"category_name": "international_outlook", "category_score": "43.5", "category_rank": "75"}, {"category_name": "industry_income", "category_score": "-", "category_rank": "81"}, {"category_name": "research", "category_score": "39.3", "category_rank": "73"}, {"category_name": "citations", "category_score": "57.1", "category_rank": "54"}]}, {"name": "Northwestern University", "country": "United States", "ranking_categories": [{"category_name": "overall", "category_score": "47.7", "category_rank": "58"}, {"category_name": "teaching", "category_score": "46.4", "category_rank": "61"}, {"category_name": "international_outlook", "category_score": "29.6", "category_rank": "100"}, {"category_name": "industry_income", "category_score": "36.8", "category_rank": "71"}, {"category_name": "research", "category_score": "43.6", "category_rank": "62"}, {"category_name": "citations", "category_score": "72.2", "category_rank": "11"}]}, {"name": "University of Leeds", "country": "United Kingdom", "ranking_categories": [{"category_name": "overall", "category_score": "47.5", "category_rank": "60"}, {"category_name": "teaching", "category_score": "43.9", "category_rank": "67"}, {"category_name": "international_outlook", "category_score": "53.1", "category_rank": "58"}, {"category_name": "industry_income", "category_score": "39.0", "category_rank": "40"}, {"category_name": "research", "category_score": "46.5", "category_rank": "56"}, {"category_name": "citations", "category_score": "57.5", "category_rank": "52"}]}, {"name": "Ohio State University (Main campus)", "country": "United States", "ranking_categories": [{"category_name": "overall", "category_score": "47.5", "category_rank": "59"}, {"category_name": "teaching", "category_score": "44.1", "category_rank": "66"}, {"category_name": "international_outlook", "category_score": "47.2", "category_rank": "70"}, {"category_name": "industry_income", "category_score": "37.4", "category_rank": "58"}, {"category_name": "research", "category_score": "43.0", "category_rank": "66"}, {"category_name": "citations", "category_score": "69.4", "category_rank": "18"}]}, {"name": "University of Glasgow", "country": "United Kingdom", "ranking_categories": [{"category_name": "overall", "category_score": "47.0", "category_rank": "61"}, {"category_name": "teaching", "category_score": "45.3", "category_rank": "63"}, {"category_name": "international_outlook", "category_score": "59.5", "category_rank": "50"}, {"category_name": "industry_income", "category_score": "37.9", "category_rank": "48"}, {"category_name": "research", "category_score": "44.9", "category_rank": "60"}, {"category_name": "citations", "category_score": "51.7", "category_rank": "71"}]}, {"name": "University of Illinois at Urbana-Champaign", "country": "United States", "ranking_categories": [{"category_name": "overall", "category_score": "46.4", "category_rank": "62"}, {"category_name": "teaching", "category_score": "48.1", "category_rank": "53"}, {"category_name": "international_outlook", "category_score": "38.2", "category_rank": "84"}, {"category_name": "industry_income", "category_score": "-", "category_rank": "93"}, {"category_name": "research", "category_score": "39.3", "category_rank": "74"}, {"category_name": "citations", "category_score": "65.0", "category_rank": "31"}]}, {"name": "University of Virginia (Main campus)", "country": "United States", "ranking_categories": [{"category_name": "overall", "category_score": "46.0", "category_rank": "63"}, {"category_name": "teaching", "category_score": "46.5", "category_rank": "60"}, {"category_name": "international_outlook", "category_score": "36.9", "category_rank": "88"}, {"category_name": "industry_income", "category_score": "39.6", "category_rank": "36"}, {"category_name": "research", "category_score": "43.5", "category_rank": "63"}, {"category_name": "citations", "category_score": "56.3", "category_rank": "58"}]}, {"name": "University of York", "country": "United Kingdom", "ranking_categories": [{"category_name": "overall", "category_score": "45.9", "category_rank": "64"}, {"category_name": "teaching", "category_score": "42.0", "category_rank": "71"}, {"category_name": "international_outlook", "category_score": "62.1", "category_rank": "43"}, {"category_name": "industry_income", "category_score": "36.8", "category_rank": "75"}, {"category_name": "research", "category_score": "37.5", "category_rank": "80"}, {"category_name": "citations", "category_score": "70.0", "category_rank": "16"}]}, {"name": "University of Exeter", "country": "United Kingdom", "ranking_categories": [{"category_name": "overall", "category_score": "45.3", "category_rank": "65"}, {"category_name": "teaching", "category_score": "40.0", "category_rank": "74"}, {"category_name": "international_outlook", "category_score": "69.6", "category_rank": "24"}, {"category_name": "industry_income", "category_score": "37.8", "category_rank": "50"}, {"category_name": "research", "category_score": "40.1", "category_rank": "70"}, {"category_name": "citations", "category_score": "60.6", "category_rank": "46"}]}, {"name": "University of Helsinki", "country": "Finland", "ranking_categories": [{"category_name": "overall", "category_score": "45.3", "category_rank": "66"}, {"category_name": "teaching", "category_score": "45.1", "category_rank": "64"}, {"category_name": "international_outlook", "category_score": "48.8", "category_rank": "69"}, {"category_name": "industry_income", "category_score": "36.9", "category_rank": "66"}, {"category_name": "research", "category_score": "45.1", "category_rank": "59"}, {"category_name": "citations", "category_score": "45.9", "category_rank": "83"}]}, {"name": "The University of Queensland", "country": "Australia", "ranking_categories": [{"category_name": "overall", "category_score": "45.1", "category_rank": "68"}, {"category_name": "teaching", "category_score": "36.3", "category_rank": "82"}, {"category_name": "international_outlook", "category_score": "75.8", "category_rank": "13"}, {"category_name": "industry_income", "category_score": "42.3", "category_rank": "26"}, {"category_name": "research", "category_score": "45.2", "category_rank": "58"}, {"category_name": "citations", "category_score": "51.9", "category_rank": "69"}]}, {"name": "Macquarie University", "country": "Australia", "ranking_categories": [{"category_name": "overall", "category_score": "45.1", "category_rank": "67"}, {"category_name": "teaching", "category_score": "39.2", "category_rank": "75"}, {"category_name": "international_outlook", "category_score": "83.0", "category_rank": "6"}, {"category_name": "industry_income", "category_score": "40.3", "category_rank": "34"}, {"category_name": "research", "category_score": "38.9", "category_rank": "76"}, {"category_name": "citations", "category_score": "57.3", "category_rank": "53"}]}, {"name": "Ghent University", "country": "Belgium", "ranking_categories": [{"category_name": "overall", "category_score": "44.8", "category_rank": "69"}, {"category_name": "teaching", "category_score": "32.9", "category_rank": "95"}, {"category_name": "international_outlook", "category_score": "52.5", "category_rank": "61"}, {"category_name": "industry_income", "category_score": "80.7", "category_rank": "3"}, {"category_name": "research", "category_score": "44.3", "category_rank": "61"}, {"category_name": "citations", "category_score": "66.2", "category_rank": "27"}]}, {"name": "Chinese University of Hong Kong", "country": "Hong Kong", "ranking_categories": [{"category_name": "overall", "category_score": "44.7", "category_rank": "70"}, {"category_name": "teaching", "category_score": "44.6", "category_rank": "65"}, {"category_name": "international_outlook", "category_score": "71.3", "category_rank": "21"}, {"category_name": "industry_income", "category_score": "40.8", "category_rank": "33"}, {"category_name": "research", "category_score": "38.9", "category_rank": "75"}, {"category_name": "citations", "category_score": "47.1", "category_rank": "81"}]}, {"name": "Boston University", "country": "United States", "ranking_categories": [{"category_name": "overall", "category_score": "44.6", "category_rank": "71"}, {"category_name": "teaching", "category_score": "47.5", "category_rank": "57"}, {"category_name": "international_outlook", "category_score": "41.9", "category_rank": "77"}, {"category_name": "industry_income", "category_score": "36.8", "category_rank": "67"}, {"category_name": "research", "category_score": "32.6", "category_rank": "92"}, {"category_name": "citations", "category_score": "69.8", "category_rank": "17"}]}, {"name": "National Autonomous University of Mexico", "country": "Mexico", "ranking_categories": [{"category_name": "overall", "category_score": "44.3", "category_rank": "72"}, {"category_name": "teaching", "category_score": "42.7", "category_rank": "69"}, {"category_name": "international_outlook", "category_score": "37.9", "category_rank": "85"}, {"category_name": "industry_income", "category_score": "83.6", "category_rank": "2"}, {"category_name": "research", "category_score": "47.1", "category_rank": "55"}, {"category_name": "citations", "category_score": "38.1", "category_rank": "99"}]}, {"name": "University of Nottingham", "country": "United Kingdom", "ranking_categories": [{"category_name": "overall", "category_score": "44.2", "category_rank": "73"}, {"category_name": "teaching", "category_score": "46.2", "category_rank": "62"}, {"category_name": "international_outlook", "category_score": "66.9", "category_rank": "28"}, {"category_name": "industry_income", "category_score": "39.7", "category_rank": "35"}, {"category_name": "research", "category_score": "39.7", "category_rank": "72"}, {"category_name": "citations", "category_score": "40.1", "category_rank": "97"}]}, {"name": "Lund University", "country": "Sweden", "ranking_categories": [{"category_name": "overall", "category_score": "43.6", "category_rank": "74"}, {"category_name": "teaching", "category_score": "36.6", "category_rank": "81"}, {"category_name": "international_outlook", "category_score": "61.8", "category_rank": "44"}, {"category_name": "industry_income", "category_score": "37.1", "category_rank": "60"}, {"category_name": "research", "category_score": "43.1", "category_rank": "65"}, {"category_name": "citations", "category_score": "54.4", "category_rank": "62"}]}, {"name": "Utrecht University", "country": "Netherlands", "ranking_categories": [{"category_name": "overall", "category_score": "43.5", "category_rank": "76"}, {"category_name": "teaching", "category_score": "38.4", "category_rank": "76"}, {"category_name": "international_outlook", "category_score": "53.1", "category_rank": "59"}, {"category_name": "industry_income", "category_score": "-", "category_rank": "101"}, {"category_name": "research", "category_score": "38.1", "category_rank": "79"}, {"category_name": "citations", "category_score": "65.8", "category_rank": "28"}]}, {"name": "Emory University", "country": "United States", "ranking_categories": [{"category_name": "overall", "category_score": "43.5", "category_rank": "75"}, {"category_name": "teaching", "category_score": "47.8", "category_rank": "55"}, {"category_name": "international_outlook", "category_score": "36.3", "category_rank": "90"}, {"category_name": "industry_income", "category_score": "36.8", "category_rank": "69"}, {"category_name": "research", "category_score": "31.8", "category_rank": "93"}, {"category_name": "citations", "category_score": "66.5", "category_rank": "26"}]}, {"name": "Sapienza University of Rome", "country": "Italy", "ranking_categories": [{"category_name": "overall", "category_score": "42.7", "category_rank": "77"}, {"category_name": "teaching", "category_score": "46.7", "category_rank": "59"}, {"category_name": "international_outlook", "category_score": "31.1", "category_rank": "99"}, {"category_name": "industry_income", "category_score": "47.6", "category_rank": "20"}, {"category_name": "research", "category_score": "48.3", "category_rank": "53"}, {"category_name": "citations", "category_score": "23.6", "category_rank": "100"}]}, {"name": "University of Bristol", "country": "United Kingdom", "ranking_categories": [{"category_name": "overall", "category_score": "42.1", "category_rank": "78"}, {"category_name": "teaching", "category_score": "34.5", "category_rank": "91"}, {"category_name": "international_outlook", "category_score": "63.2", "category_rank": "38"}, {"category_name": "industry_income", "category_score": "37.7", "category_rank": "51"}, {"category_name": "research", "category_score": "35.1", "category_rank": "82"}, {"category_name": "citations", "category_score": "68.2", "category_rank": "22"}]}, {"name": "University of California, Santa Cruz", "country": "United States", "ranking_categories": [{"category_name": "overall", "category_score": "41.7", "category_rank": "79"}, {"category_name": "teaching", "category_score": "42.7", "category_rank": "70"}, {"category_name": "international_outlook", "category_score": "34.7", "category_rank": "92"}, {"category_name": "industry_income", "category_score": "-", "category_rank": "91"}, {"category_name": "research", "category_score": "33.5", "category_rank": "89"}, {"category_name": "citations", "category_score": "63.8", "category_rank": "36"}]}, {"name": "University of Cape Town", "country": "South Africa", "ranking_categories": [{"category_name": "overall", "category_score": "41.1", "category_rank": "80"}, {"category_name": "teaching", "category_score": "35.4", "category_rank": "87"}, {"category_name": "international_outlook", "category_score": "64.9", "category_rank": "34"}, {"category_name": "industry_income", "category_score": "68.2", "category_rank": "7"}, {"category_name": "research", "category_score": "41.1", "category_rank": "69"}, {"category_name": "citations", "category_score": "39.0", "category_rank": "98"}]}, {"name": "University of Groningen", "country": "Netherlands", "ranking_categories": [{"category_name": "overall", "category_score": "40.6", "category_rank": "81"}, {"category_name": "teaching", "category_score": "33.7", "category_rank": "93"}, {"category_name": "international_outlook", "category_score": "62.1", "category_rank": "42"}, {"category_name": "industry_income", "category_score": "53.3", "category_rank": "16"}, {"category_name": "research", "category_score": "38.9", "category_rank": "77"}, {"category_name": "citations", "category_score": "48.9", "category_rank": "76"}]}, {"name": "University of Zurich", "country": "Switzerland", "ranking_categories": [{"category_name": "overall", "category_score": "40.5", "category_rank": "82"}, {"category_name": "teaching", "category_score": "36.1", "category_rank": "83"}, {"category_name": "international_outlook", "category_score": "83.8", "category_rank": "5"}, {"category_name": "industry_income", "category_score": "-", "category_rank": "100"}, {"category_name": "research", "category_score": "26.5", "category_rank": "101"}, {"category_name": "citations", "category_score": "65.7", "category_rank": "30"}]}, {"name": "Stockholm University", "country": "Sweden", "ranking_categories": [{"category_name": "overall", "category_score": "39.8", "category_rank": "83"}, {"category_name": "teaching", "category_score": "35.6", "category_rank": "86"}, {"category_name": "international_outlook", "category_score": "45.9", "category_rank": "71"}, {"category_name": "industry_income", "category_score": "37.6", "category_rank": "52"}, {"category_name": "research", "category_score": "36.5", "category_rank": "81"}, {"category_name": "citations", "category_score": "55.6", "category_rank": "59"}]}, {"name": "University of Bologna", "country": "Italy", "ranking_categories": [{"category_name": "overall", "category_score": "39.7", "category_rank": "84"}, {"category_name": "teaching", "category_score": "40.0", "category_rank": "73"}, {"category_name": "international_outlook", "category_score": "40.1", "category_rank": "81"}, {"category_name": "industry_income", "category_score": "37.9", "category_rank": "47"}, {"category_name": "research", "category_score": "38.5", "category_rank": "78"}, {"category_name": "citations", "category_score": "42.0", "category_rank": "96"}]}, {"name": "University of Washington", "country": "United States", "ranking_categories": [{"category_name": "overall", "category_score": "39.3", "category_rank": "86"}, {"category_name": "teaching", "category_score": "35.7", "category_rank": "85"}, {"category_name": "international_outlook", "category_score": "52.8", "category_rank": "60"}, {"category_name": "industry_income", "category_score": "-", "category_rank": "99"}, {"category_name": "research", "category_score": "34.7", "category_rank": "84"}, {"category_name": "citations", "category_score": "53.9", "category_rank": "64"}]}, {"name": "University of Maryland, College Park", "country": "United States", "ranking_categories": [{"category_name": "overall", "category_score": "39.3", "category_rank": "85"}, {"category_name": "teaching", "category_score": "37.2", "category_rank": "77"}, {"category_name": "international_outlook", "category_score": "32.3", "category_rank": "96"}, {"category_name": "industry_income", "category_score": "37.6", "category_rank": "53"}, {"category_name": "research", "category_score": "34.2", "category_rank": "87"}, {"category_name": "citations", "category_score": "61.1", "category_rank": "44"}]}, {"name": "Vrije Universiteit Amsterdam", "country": "Netherlands", "ranking_categories": [{"category_name": "overall", "category_score": "39.0", "category_rank": "89"}, {"category_name": "teaching", "category_score": "33.8", "category_rank": "92"}, {"category_name": "international_outlook", "category_score": "49.2", "category_rank": "68"}, {"category_name": "industry_income", "category_score": "67.1", "category_rank": "8"}, {"category_name": "research", "category_score": "31.1", "category_rank": "94"}, {"category_name": "citations", "category_score": "61.9", "category_rank": "43"}]}, {"name": "Complutense University of Madrid", "country": "Spain", "ranking_categories": [{"category_name": "overall", "category_score": "39.0", "category_rank": "87"}, {"category_name": "teaching", "category_score": "43.3", "category_rank": "68"}, {"category_name": "international_outlook", "category_score": "31.5", "category_rank": "98"}, {"category_name": "industry_income", "category_score": "-", "category_rank": "78"}, {"category_name": "research", "category_score": "43.1", "category_rank": "64"}, {"category_name": "citations", "category_score": "23.4", "category_rank": "101"}]}, {"name": "University of Sheffield", "country": "United Kingdom", "ranking_categories": [{"category_name": "overall", "category_score": "39.0", "category_rank": "88"}, {"category_name": "teaching", "category_score": "37.0", "category_rank": "79"}, {"category_name": "international_outlook", "category_score": "60.6", "category_rank": "47"}, {"category_name": "industry_income", "category_score": "37.3", "category_rank": "59"}, {"category_name": "research", "category_score": "34.8", "category_rank": "83"}, {"category_name": "citations", "category_score": "43.6", "category_rank": "91"}]}, {"name": "Autonomous University of Barcelona", "country": "Spain", "ranking_categories": [{"category_name": "overall", "category_score": "38.8", "category_rank": "90"}, {"category_name": "teaching", "category_score": "34.9", "category_rank": "89"}, {"category_name": "international_outlook", "category_score": "50.6", "category_rank": "63"}, {"category_name": "industry_income", "category_score": "46.1", "category_rank": "22"}, {"category_name": "research", "category_score": "34.3", "category_rank": "86"}, {"category_name": "citations", "category_score": "52.6", "category_rank": "67"}]}, {"name": "Aarhus University", "country": "Denmark", "ranking_categories": [{"category_name": "overall", "category_score": "38.7", "category_rank": "91"}, {"category_name": "teaching", "category_score": "27.8", "category_rank": "101"}, {"category_name": "international_outlook", "category_score": "61.5", "category_rank": "45"}, {"category_name": "industry_income", "category_score": "66.7", "category_rank": "9"}, {"category_name": "research", "category_score": "32.9", "category_rank": "91"}, {"category_name": "citations", "category_score": "64.6", "category_rank": "32"}]}, {"name": "Radboud University Nijmegen", "country": "Netherlands", "ranking_categories": [{"category_name": "overall", "category_score": "38.3", "category_rank": "92"}, {"category_name": "teaching", "category_score": "30.3", "category_rank": "99"}, {"category_name": "international_outlook", "category_score": "71.7", "category_rank": "19"}, {"category_name": "industry_income", "category_score": "37.5", "category_rank": "55"}, {"category_name": "research", "category_score": "30.1", "category_rank": "96"}, {"category_name": "citations", "category_score": "62.2", "category_rank": "42"}]}, {"name": "Victoria University of Wellington", "country": "New Zealand", "ranking_categories": [{"category_name": "overall", "category_score": "38.3", "category_rank": "93"}, {"category_name": "teaching", "category_score": "30.9", "category_rank": "97"}, {"category_name": "international_outlook", "category_score": "71.4", "category_rank": "20"}, {"category_name": "industry_income", "category_score": "48.5", "category_rank": "19"}, {"category_name": "research", "category_score": "33.2", "category_rank": "90"}, {"category_name": "citations", "category_score": "51.6", "category_rank": "72"}]}, {"name": "University of Minnesota", "country": "United States", "ranking_categories": [{"category_name": "overall", "category_score": "38.2", "category_rank": "95"}, {"category_name": "teaching", "category_score": "32.5", "category_rank": "96"}, {"category_name": "international_outlook", "category_score": "33.1", "category_rank": "95"}, {"category_name": "industry_income", "category_score": "-", "category_rank": "94"}, {"category_name": "research", "category_score": "40.0", "category_rank": "71"}, {"category_name": "citations", "category_score": "51.4", "category_rank": "73"}]}, {"name": "Hebrew University of Jerusalem", "country": "Israel", "ranking_categories": [{"category_name": "overall", "category_score": "38.2", "category_rank": "94"}, {"category_name": "teaching", "category_score": "37.1", "category_rank": "78"}, {"category_name": "international_outlook", "category_score": "52.2", "category_rank": "62"}, {"category_name": "industry_income", "category_score": "-", "category_rank": "82"}, {"category_name": "research", "category_score": "34.4", "category_rank": "85"}, {"category_name": "citations", "category_score": "42.7", "category_rank": "95"}]}, {"name": "Tel Aviv University", "country": "Israel", "ranking_categories": [{"category_name": "overall", "category_score": "37.6", "category_rank": "96"}, {"category_name": "teaching", "category_score": "35.8", "category_rank": "84"}, {"category_name": "international_outlook", "category_score": "45.8", "category_rank": "72"}, {"category_name": "industry_income", "category_score": "37.8", "category_rank": "49"}, {"category_name": "research", "category_score": "33.8", "category_rank": "88"}, {"category_name": "citations", "category_score": "47.3", "category_rank": "80"}]}, {"name": "York University", "country": "Canada", "ranking_categories": [{"category_name": "overall", "category_score": "37.2", "category_rank": "97"}, {"category_name": "teaching", "category_score": "34.7", "category_rank": "90"}, {"category_name": "international_outlook", "category_score": "45.0", "category_rank": "73"}, {"category_name": "industry_income", "category_score": "52.7", "category_rank": "18"}, {"category_name": "research", "category_score": "29.8", "category_rank": "98"}, {"category_name": "citations", "category_score": "55.2", "category_rank": "61"}]}, {"name": "University of California, Irvine", "country": "United States", "ranking_categories": [{"category_name": "overall", "category_score": "36.6", "category_rank": "98"}, {"category_name": "teaching", "category_score": "30.6", "category_rank": "98"}, {"category_name": "international_outlook", "category_score": "41.8", "category_rank": "78"}, {"category_name": "industry_income", "category_score": "36.8", "category_rank": "72"}, {"category_name": "research", "category_score": "29.1", "category_rank": "99"}, {"category_name": "citations", "category_score": "67.6", "category_rank": "24"}]}, {"name": "La Trobe University", "country": "Australia", "ranking_categories": [{"category_name": "overall", "category_score": "36.4", "category_rank": "99"}, {"category_name": "teaching", "category_score": "33.5", "category_rank": "94"}, {"category_name": "international_outlook", "category_score": "63.2", "category_rank": "37"}, {"category_name": "industry_income", "category_score": "74.7", "category_rank": "5"}, {"category_name": "research", "category_score": "28.5", "category_rank": "100"}, {"category_name": "citations", "category_score": "43.8", "category_rank": "88"}]}, {"name": "Goethe University Frankfurt", "country": "Germany", "ranking_categories": [{"category_name": "overall", "category_score": "36.3", "category_rank": "100"}, {"category_name": "teaching", "category_score": "35.0", "category_rank": "88"}, {"category_name": "international_outlook", "category_score": "55.8", "category_rank": "56"}, {"category_name": "industry_income", "category_score": "38.8", "category_rank": "42"}, {"category_name": "research", "category_score": "29.8", "category_rank": "97"}, {"category_name": "citations", "category_score": "45.4", "category_rank": "84"}]}, {"name": "UNSW Sydney", "country": "Australia", "ranking_categories": [{"category_name": "overall", "category_score": "36.3", "category_rank": "101"}, {"category_name": "teaching", "category_score": "29.6", "category_rank": "100"}, {"category_name": "international_outlook", "category_score": "71.9", "category_rank": "18"}, {"category_name": "industry_income", "category_score": "40.9", "category_rank": "32"}, {"category_name": "research", "category_score": "30.6", "category_rank": "95"}, {"category_name": "citations", "category_score": "49.2", "category_rank": "75"}]}]